syft_perm/__init__.py
syft_perm/_auto_recovery.py
syft_perm/_impl.py
syft_perm/_syftbox.py
syft_perm/_utils.py
syft_perm/filesystem_editor.py
syft_perm/server.py
syft_perm/static/syftbox-logo.svg
syft_perm-0.3.92.dist-info/licenses/LICENSE
syft_perm-0.3.92.dist-info/METADATA
syft_perm-0.3.92.dist-info/WHEEL
syft_perm-0.3.92.dist-info/top_level.txt
syft_perm-0.3.92.dist-info/RECORD
