Metadata-Version: 2.4
Name: syft-perm
Version: 0.3.92
Summary: Minimal utilities for managing SyftBox file permissions
Author-email: OpenMined <info@openmined.org>
License: Apache-2.0
Project-URL: Homepage, https://github.com/OpenMined/syft-perm
Project-URL: Documentation, https://github.com/OpenMined/syft-perm#readme
Project-URL: Repository, https://github.com/OpenMined/syft-perm
Project-URL: Issues, https://github.com/OpenMined/syft-perm/issues
Keywords: syftbox,permissions,privacy,federated-learning
Classifier: Development Status :: 4 - Beta
Classifier: Intended Audience :: Developers
Classifier: License :: OSI Approved :: Apache Software License
Classifier: Operating System :: OS Independent
Classifier: Programming Language :: Python :: 3
Classifier: Programming Language :: Python :: 3.9
Classifier: Programming Language :: Python :: 3.10
Classifier: Programming Language :: Python :: 3.11
Classifier: Programming Language :: Python :: 3.12
Classifier: Topic :: Security
Classifier: Topic :: Software Development :: Libraries :: Python Modules
Requires-Python: >=3.9
License-File: LICENSE
Requires-Dist: fastapi>=0.104.0
Requires-Dist: loguru>=0.7.3
Requires-Dist: pyyaml>=6.0
Requires-Dist: requests>=2.31.0
Requires-Dist: uvicorn[standard]>=0.24.0
Requires-Dist: watchdog>=6.0.0
Requires-Dist: websockets>=15.0.1
Provides-Extra: syftbox
Requires-Dist: syft-core; extra == "syftbox"
Provides-Extra: display
Requires-Dist: tabulate>=0.9.0; extra == "display"
Provides-Extra: server
Requires-Dist: fastapi>=0.104.0; extra == "server"
Requires-Dist: uvicorn>=0.24.0; extra == "server"
Requires-Dist: loguru>=0.7.0; extra == "server"
Requires-Dist: watchdog>=3.0.0; extra == "server"
Requires-Dist: websockets>=12.0; extra == "server"
Provides-Extra: dev
Requires-Dist: pytest>=7.0; extra == "dev"
Requires-Dist: pytest-cov; extra == "dev"
Requires-Dist: black; extra == "dev"
Requires-Dist: isort; extra == "dev"
Requires-Dist: flake8; extra == "dev"
Requires-Dist: mypy; extra == "dev"
Requires-Dist: nbformat>=5.9.0; extra == "dev"
Requires-Dist: nbconvert>=7.16.0; extra == "dev"
Requires-Dist: ipykernel>=6.29.0; extra == "dev"
Dynamic: license-file
